e220_900t22s/__init__.py
e220_900t22s/base_enums.py
e220_900t22s/enums.py
e220_900t22s/module.py
e220_900t22s/register.py
e220_900t22s-1.1.0.dist-info/METADATA
e220_900t22s-1.1.0.dist-info/WHEEL
e220_900t22s-1.1.0.dist-info/licenses/LICENSE
e220_900t22s-1.1.0.dist-info/RECORD
