Metadata-Version: 2.1
Name: e220_900t22s
Version: 1.1.0
Summary: E220-900T22S Python Library for Raspberry Pi.
Project-URL: Homepage, https://github.com/taogya/RPi_E220-900T22S_LoRa_library
Project-URL: Bug Tracker, https://github.com/taogya/RPi_E220-900T22S_LoRa_library/issues
Author-email: Taogya <132679709+taogya@users.noreply.github.com>
License: BSD 3-Clause License
License-File: LICENSE
Classifier: License :: OSI Approved :: BSD License
Classifier: Operating System :: POSIX :: Linux
Classifier: Programming Language :: Python :: 3
Requires-Python: >=3.9
Requires-Dist: pyserial>=3.5
Requires-Dist: rpi-gpio-helper>=2.3.0
